mcpweb/__init__.py
mcpweb/fastapi_middleware.py
mcpweb-1.0.0.dist-info/METADATA
mcpweb-1.0.0.dist-info/WHEEL
mcpweb-1.0.0.dist-info/top_level.txt
mcpweb-1.0.0.dist-info/RECORD
