Metadata-Version: 2.4
Name: mcpweb
Version: 1.0.0
Summary: FastAPI middleware for MCP Web Discovery
Author-email: John Rood <john@johnrood.com>
License: MIT
Project-URL: Source, https://github.com/John-Rood/mcp-web-discovery
Requires-Dist: fastapi>=0.110
